sandie/__init__.py
sandie/conf/__init__.py
sandie/conf/model/__init__.py
sandie/conf/model/config.py
sandie/conf/model/connection.py
sandie/model/__init__.py
sandie/model/connection.py
sandie/model/logger.py
sandie/model/source.py
sandie/model/sources/csv.py
sandie/model/sources/mysql.py
sandie/model/sources/postgresql.py
sandie/model/sources/restapi.py
sandie-1.0.2.dist-info/METADATA
sandie-1.0.2.dist-info/WHEEL
sandie-1.0.2.dist-info/top_level.txt
sandie-1.0.2.dist-info/RECORD
