Metadata-Version: 2.2
Name: sandie
Version: 1.0.2
License: MIT License
Requires-Dist: requests>=2.25.1
Requires-Dist: importlib-metadata; python_version < "3.10"
Requires-Dist: certifi==2024.8.30
Requires-Dist: charset-normalizer==3.4.0
Requires-Dist: greenlet==3.1.1
Requires-Dist: idna==3.10
Requires-Dist: numpy==2.2.0
Requires-Dist: pandas==2.2.3
Requires-Dist: python-dateutil==2.9.0.post0
Requires-Dist: pytz==2024.2
Requires-Dist: PyYAML==6.0.2
Requires-Dist: requests==2.32.3
Requires-Dist: six==1.17.0
Requires-Dist: SQLAlchemy==2.0.36
Requires-Dist: typing_extensions==4.12.2
Requires-Dist: tzdata==2024.2
Requires-Dist: urllib3==2.2.3
Requires-Dist: mysql-connector-python==9.1.0
